{
  "minecraft:recipes/tools/flint_and_steel": {
    "criteria": {
      "has_obsidian": "2024-10-10 09:31:12 +0530"
    },
    "done": true
  },
  "minecraft:story/form_obsidian": {
    "criteria": {
      "obsidian": "2024-10-10 09:31:12 +0530"
    },
    "done": true
  },
  "minecraft:recipes/decorations/crafting_table": {
    "criteria": {
      "unlock_right_away": "2024-10-10 09:31:12 +0530"
    },
    "done": true
  },
  "minecraft:recipes/decorations/chest": {
    "criteria": {
      "has_lots_of_items": "2024-10-10 09:31:12 +0530"
    },
    "done": true
  },
  "minecraft:adventure/adventuring_time": {
    "criteria": {
      "minecraft:plains": "2024-10-10 09:31:13 +0530"
    },
    "done": false
  },
  "minecraft:recipes/decorations/enchanting_table": {
    "criteria": {
      "has_obsidian": "2024-10-10 09:31:12 +0530"
    },
    "done": true
  },
  "DataVersion": 3465
}